{
  "type": "calculatedTableColumn",
  "name": "Fiscal QuarterDays",
  "dataType": "int64",
  "isNameInferred": true,
  "isDataTypeInferred": true,
  "isHidden": true,
  "sourceColumn": "[Fiscal QuarterDays]",
  "formatString": "0",
  "lineageTag": "fdb7f779-9174-494b-aa76-538fb0d71062",
  "summarizeBy": "none",
  "annotations": [
    {
      "name": "SummarizationSetBy",
      "value": "User"
    },
    {
      "name": "Format",
      "value": "<Format Format=\"NumberWhole\" Accuracy=\"0\" />"
    },
    {
      "name": "DataTypeAtRefresh",
      "value": "Int64#####not a type"
    }
  ]
}